jgwillhub/__init__.py
jgwillhub/cli.py
jgwillhub/jgwillprompts.py
tests/__init__.py
tests/test_prompts.py
jgwillhub-0.1.5.dist-info/METADATA
jgwillhub-0.1.5.dist-info/WHEEL
jgwillhub-0.1.5.dist-info/entry_points.txt
jgwillhub-0.1.5.dist-info/top_level.txt
jgwillhub-0.1.5.dist-info/RECORD
