Metadata-Version: 2.1
Name: jgwillhub
Version: 0.1.5
Summary: A prompt template hub helper for langchainhub
Home-page: https://github.com/jgwill/hub
Author: JGWill
Author-email: jgi@jgwill.com
Classifier: Programming Language :: Python :: 3
Classifier: License :: OSI Approved :: MIT License
Classifier: Operating System :: OS Independent
Requires-Python: >=3.6
Requires-Dist: requests
Requires-Dist: langchainhub
